easy_lambda/__init__.py
easy_lambda/utils.py
easy_lambda/create/README.md
easy_lambda/create/app.py
easy_lambda/create/requirements.txt
easy_lambda/create/template.yaml
easy_lambda/create/test.py
easy_lambda/others/template.yaml
easy_lambda-0.0.3.dist-info/LICENSE
easy_lambda-0.0.3.dist-info/METADATA
easy_lambda-0.0.3.dist-info/WHEEL
easy_lambda-0.0.3.dist-info/top_level.txt
easy_lambda-0.0.3.dist-info/RECORD
