Metadata-Version: 2.1
Name: easy-lambda
Version: 0.0.3
Summary: AWS Lambda와 Lambda Layer를 쉽게 배포하고 테스트 할 수 있게 도와주는 패키지입니다.
Home-page: https://github.com/da-huin/easy_lambda
Author: JunYeong Park
Author-email: dahuin000@gmail.com
License: MIT
Download-URL: https://github.com/da-huin/easy_lambda/archive/master.zip
Platform: UNKNOWN
Classifier: Programming Language :: Python :: 3
Requires-Dist: boto3
Requires-Dist: pyzip
Requires-Dist: pyyaml
Requires-Dist: pyfolder
